cherry_picker/__init__.py
cherry_picker/__main__.py
cherry_picker/_version.py
cherry_picker/cherry_picker.py
cherry_picker/test_cherry_picker.py
cherry_picker-2.6.0.dist-info/METADATA
cherry_picker-2.6.0.dist-info/WHEEL
cherry_picker-2.6.0.dist-info/entry_points.txt
cherry_picker-2.6.0.dist-info/licenses/LICENSE
cherry_picker-2.6.0.dist-info/RECORD
