Metadata-Version: 2.4
Name: cherry-picker
Version: 2.6.0
Summary: Backport CPython changes from main to maintenance branches
Project-URL: Homepage, https://github.com/python/cherry-picker
Author-email: Mariatta Wijaya <mariatta@python.org>
Maintainer-email: Python Core Developers <core-workflow@python.org>
License-Expression: Apache-2.0
License-File: LICENSE
Classifier: Intended Audience :: Developers
Classifier: Programming Language :: Python :: 3 :: Only
Classifier: Programming Language :: Python :: 3.9
Classifier: Programming Language :: Python :: 3.10
Classifier: Programming Language :: Python :: 3.11
Classifier: Programming Language :: Python :: 3.12
Classifier: Programming Language :: Python :: 3.13
Classifier: Programming Language :: Python :: 3.14
Requires-Python: >=3.9
Requires-Dist: click>=6
Requires-Dist: gidgethub
Requires-Dist: requests
Requires-Dist: stamina
Requires-Dist: tomli>=1.1; python_version < '3.11'
Provides-Extra: dev
Requires-Dist: pytest; extra == 'dev'
Requires-Dist: pytest-cov; extra == 'dev'
